{
  "color": {
    "support": {
      "background-default": {
        "value": "{color.extra1.background-default}",
        "type": "color"
      },
      "background-tinted": {
        "value": "{color.extra1.background-tinted}",
        "type": "color"
      },
      "surface-tinted": {
        "value": "{color.extra1.surface-tinted}",
        "type": "color"
      },
      "surface-hover": {
        "value": "{color.extra1.surface-hover}",
        "type": "color"
      },
      "surface-active": {
        "value": "{color.extra1.surface-active}",
        "type": "color"
      },
      "border-subtle": {
        "value": "{color.extra1.border-subtle}",
        "type": "color"
      },
      "border-default": {
        "value": "{color.extra1.border-default}",
        "type": "color"
      },
      "border-strong": {
        "value": "{color.extra1.border-strong}",
        "type": "color"
      },
      "base-default": {
        "value": "{color.extra1.base-default}",
        "type": "color"
      },
      "base-hover": {
        "value": "{color.extra1.base-hover}",
        "type": "color"
      },
      "base-active": {
        "value": "{color.extra1.base-active}",
        "type": "color"
      },
      "text-subtle": {
        "value": "{color.extra1.text-subtle}",
        "type": "color"
      },
      "text-default": {
        "value": "{color.extra1.text-default}",
        "type": "color"
      },
      "base-contrast-default": {
        "value": "{color.extra1.base-contrast-default}",
        "type": "color"
      },
      "base-contrast-subtle": {
        "value": "{color.extra1.base-contrast-subtle}",
        "type": "color"
      },
      "surface-default": {
        "value": "{color.extra1.surface-default}",
        "type": "color"
      }
    }
  }
}